LICENSE
MANIFEST.in
README.md
README.rst
setup.py
flaskJSONRPCServer/__init__.py
flaskJSONRPCServer/__main__.py
flaskJSONRPCServer/gmultiprocessing.py
flaskJSONRPCServer/utils.py
flaskJSONRPCServer/virtVar.py
flaskJSONRPCServer.egg-info/PKG-INFO
flaskJSONRPCServer.egg-info/SOURCES.txt
flaskJSONRPCServer.egg-info/dependency_links.txt
flaskJSONRPCServer.egg-info/requires.txt
flaskJSONRPCServer.egg-info/top_level.txt
flaskJSONRPCServer/example/auth.py
flaskJSONRPCServer/example/hotReload1.py
flaskJSONRPCServer/example/hotReload2.py
flaskJSONRPCServer/example/hotReload_and_parallelExecuting.py
flaskJSONRPCServer/example/mergeFlaskApp.py
flaskJSONRPCServer/example/multiple.py
flaskJSONRPCServer/example/notify.py
flaskJSONRPCServer/example/parallelExecuting.py
flaskJSONRPCServer/example/parallelExecuting_manualConfig.py
flaskJSONRPCServer/example/restart.py
flaskJSONRPCServer/example/rr1.py
flaskJSONRPCServer/example/sexyPrime.py
flaskJSONRPCServer/example/simple.py
flaskJSONRPCServer/execBackend/__init__.py
flaskJSONRPCServer/execBackend/parallelWithSocket.py
flaskJSONRPCServer/execBackend/threaded.py
flaskJSONRPCServer/experimental/__init__.py