Metadata-Version: 1.1
Name: flaskJSONRPCServer
Version: 0.9.3
Summary: A Python JSON-RPC over HTTP with flask and gevent
Home-page: https://byaka.github.io/flaskJSONRPCServer/
Author: Jhon Byaka
Author-email: byaka.life@gmail.com
License: Apache 2.0
Download-URL: https://github.com/byaka/flaskJSONRPCServer/tarball/master
Keywords: flask json-rpc jsonrpc gevent
Platform: UNKNOWN
Classifier: Environment :: Web Environment
Classifier: Framework :: Flask
Classifier: Intended Audience :: Developers
Classifier: Operating System :: OS Independent
Classifier: Programming Language :: Python
Requires: python (>= 2.6)
Requires: flask (>= 0.10)
